iniloader/__init__.py
iniloader/iniloader.py
iniloader-1.0.0.dist-info/METADATA
iniloader-1.0.0.dist-info/WHEEL
iniloader-1.0.0.dist-info/top_level.txt
iniloader-1.0.0.dist-info/RECORD
