Metadata-Version: 2.1
Name: iniloader
Version: 1.0.0
Summary: iniファイルの読み書き
Author: Ruchi
Author-email: t@ruchi.main.jp
